hrtools/__init__.py
hrtools/glassdoor.py
hrtools/utils.py
hrtools-1.1.2.dist-info/LICENSE
hrtools-1.1.2.dist-info/METADATA
hrtools-1.1.2.dist-info/WHEEL
hrtools-1.1.2.dist-info/entry_points.txt
hrtools-1.1.2.dist-info/top_level.txt
hrtools-1.1.2.dist-info/RECORD
