Metadata-Version: 2.1
Name: hrtools
Version: 1.1.2
Summary: A Python package to get relevant information from HR data repositories.
Home-page: https://github.com/paulo663636/HRtools
Author: Paulo Vinicius Antunes Sá de Oliveira
Author-email: paulo.oliversa@gmail.com
License: MIT
Platform: UNKNOWN
Classifier: License :: OSI Approved :: MIT License
Classifier: Programming Language :: Python :: 3
Classifier: Programming Language :: Python :: 3.7
Requires-Dist: requests
Requires-Dist: bs4
Requires-Dist: pandas
